pyrams/__init__.py
pyrams/_version.py
pyrams/data_tools.py
pyrams/rams-vars.json
pyrams/thermo.py
pyrams/xarray.py
pyrams-0.8.8.dist-info/LICENSE
pyrams-0.8.8.dist-info/METADATA
pyrams-0.8.8.dist-info/WHEEL
pyrams-0.8.8.dist-info/top_level.txt
pyrams-0.8.8.dist-info/RECORD
